{
  "strategy_id": "theme_policy",
  "strategy_name": "테마/정책",
  "date": "20260424",
  "selected_at": "2026-04-27 18:30:51",
  "count": 5,
  "candidates": [
    {
      "code": "373220",
      "name": "LG에너지솔루션",
      "price": 464000,
      "change_pct": -3.53,
      "score": 77.4,
      "score_detail": {
        "theme_relevance": 40.0,
        "change_pct": 2.4,
        "trading_value": 20.0,
        "theme_strength": 15.0,
        "themes": [
          "기계·장비",
          "코스닥 150 정보기술",
          "코스닥 150 필수소비재",
          "일반서비스",
          "기계·장비",
          "화학",
          "코스닥 150 소재",
          "의료·정밀기기",
          "비금속",
          "금속"
        ]
      },
      "rank": 1,
      "market_cap": 0,
      "volume": 500,
      "trading_value": 1085760000000
    },
    {
      "code": "034020",
      "name": "두산에너빌리티",
      "price": 128900,
      "change_pct": 1.42,
      "score": 73.8,
      "score_detail": {
        "theme_relevance": 40.0,
        "change_pct": 3.5,
        "trading_value": 15.2,
        "theme_strength": 15.0,
        "themes": [
          "기계·장비",
          "코스닥 150 정보기술",
          "코스닥 150 필수소비재",
          "일반서비스",
          "기계·장비",
          "화학",
          "코스닥 150 소재",
          "의료·정밀기기",
          "비금속",
          "금속"
        ]
      },
      "rank": 2,
      "market_cap": 0,
      "volume": 5000,
      "trading_value": 825683000000
    },
    {
      "code": "012450",
      "name": "한화에어로스페이스",
      "price": 1454000,
      "change_pct": -0.62,
      "score": 72.3,
      "score_detail": {
        "theme_relevance": 40.0,
        "change_pct": 3.5,
        "trading_value": 13.8,
        "theme_strength": 15.0,
        "themes": [
          "기계·장비",
          "코스닥 150 정보기술",
          "코스닥 150 필수소비재",
          "일반서비스",
          "기계·장비",
          "화학",
          "코스닥 150 소재",
          "의료·정밀기기",
          "비금속",
          "금속"
        ]
      },
      "rank": 3,
      "market_cap": 0,
      "volume": 5000,
      "trading_value": 749732000000
    },
    {
      "code": "329180",
      "name": "HD현대중공업",
      "price": 673000,
      "change_pct": 0.3,
      "score": 68.8,
      "score_detail": {
        "theme_relevance": 40.0,
        "change_pct": 0.8,
        "trading_value": 13.0,
        "theme_strength": 15.0,
        "themes": [
          "기계·장비",
          "코스닥 150 정보기술",
          "코스닥 150 필수소비재",
          "일반서비스",
          "기계·장비",
          "화학",
          "코스닥 150 소재",
          "의료·정밀기기",
          "비금속",
          "금속"
        ]
      },
      "rank": 4,
      "market_cap": 0,
      "volume": 5000,
      "trading_value": 706389000000
    },
    {
      "code": "009150",
      "name": "삼성전기",
      "price": 794000,
      "change_pct": 0.76,
      "score": 67.8,
      "score_detail": {
        "theme_relevance": 40.0,
        "change_pct": 1.9,
        "trading_value": 10.9,
        "theme_strength": 15.0,
        "themes": [
          "기계·장비",
          "코스닥 150 정보기술",
          "코스닥 150 필수소비재",
          "일반서비스",
          "기계·장비",
          "화학",
          "코스닥 150 소재",
          "의료·정밀기기",
          "비금속",
          "금속"
        ]
      },
      "rank": 5,
      "market_cap": 0,
      "volume": 5000,
      "trading_value": 593068000000
    }
  ],
  "params": {
    "active_themes": [
      {
        "name": "기계·장비",
        "change_pct": 4.44
      },
      {
        "name": "코스닥 150 정보기술",
        "change_pct": 4.27
      },
      {
        "name": "코스닥 150 필수소비재",
        "change_pct": 4.09
      },
      {
        "name": "일반서비스",
        "change_pct": 3.85
      },
      {
        "name": "기계·장비",
        "change_pct": 3.44
      },
      {
        "name": "화학",
        "change_pct": 3.36
      },
      {
        "name": "코스닥 150 소재",
        "change_pct": 3.3
      },
      {
        "name": "의료·정밀기기",
        "change_pct": 3.18
      },
      {
        "name": "비금속",
        "change_pct": 3.13
      },
      {
        "name": "금속",
        "change_pct": 3.08
      }
    ],
    "theme_count": 10,
    "total_stocks": 72,
    "weights": {
      "theme_relevance": 40,
      "change_pct": 25,
      "trading_value": 20,
      "theme_strength": 15
    }
  },
  "simulation": null
}