{
  "date": "20260427",
  "status": "success",
  "teams": {
    "team_a": {
      "team_id": "team_a",
      "team_name": "Alpha Momentum",
      "strategy_id": "momentum",
      "status": "success",
      "selection": {
        "strategy_id": "momentum",
        "strategy_name": "모멘텀 추세",
        "date": "20260424",
        "selected_at": "2026-04-27 18:30:06",
        "count": 5,
        "candidates": [
          {
            "code": "006340",
            "name": "대원전선",
            "price": 9020,
            "change_pct": 10.81,
            "score": 91.3,
            "score_detail": {
              "change_pct": 26.25607217210271,
              "trading_value": 30.0,
              "volume_surge": 20,
              "price_level": 15
            },
            "rank": 1,
            "market_cap": 0,
            "volume": 116448411,
            "trading_value": 1033431895775
          },
          {
            "code": "289930",
            "name": "웨이비스",
            "price": 22600,
            "change_pct": 13.0,
            "score": 67.6,
            "score_detail": {
              "change_pct": 31.575294934073558,
              "trading_value": 1.0578122331711035,
              "volume_surge": 20,
              "price_level": 15
            },
            "rank": 2,
            "market_cap": 0,
            "volume": 1611419,
            "trading_value": 36439230050
          },
          {
            "code": "089030",
            "name": "테크윙",
            "price": 61800,
            "change_pct": 12.36,
            "score": 66.2,
            "score_detail": {
              "change_pct": 30.020818875780705,
              "trading_value": 8.726942709404783,
              "volume_surge": 20,
              "price_level": 7.5
            },
            "rank": 3,
            "market_cap": 0,
            "volume": 4983557,
            "trading_value": 300623364950
          },
          {
            "code": "232140",
            "name": "와이씨",
            "price": 23300,
            "change_pct": 10.95,
            "score": 64.5,
            "score_detail": {
              "change_pct": 26.596113809854266,
              "trading_value": 2.9232658142261703,
              "volume_surge": 20,
              "price_level": 15
            },
            "rank": 4,
            "market_cap": 0,
            "volume": 4422903,
            "trading_value": 100699871075
          },
          {
            "code": "019210",
            "name": "와이지-원",
            "price": 16560,
            "change_pct": 11.29,
            "score": 63.8,
            "score_detail": {
              "change_pct": 27.42192921582234,
              "trading_value": 1.4233693572975012,
              "volume_surge": 20,
              "price_level": 15
            },
            "rank": 5,
            "market_cap": 0,
            "volume": 2966916,
            "trading_value": 49031843110
          }
        ],
        "params": {
          "min_price": 3000,
          "min_change": 3.0,
          "max_change": 15.0,
          "min_trading_value": 30,
          "weights": {
            "change_pct": 35,
            "trading_value": 30,
            "volume_surge": 20,
            "price_level": 15
          }
        },
        "simulation": null
      },
      "simulation": {
        "date": "20260427",
        "strategy_id": "momentum",
        "strategy_name": "Alpha Momentum",
        "total_trades": 5,
        "wins": 3,
        "losses": 2,
        "win_rate": 60.0,
        "total_return": 3.05,
        "avg_return": 0.61,
        "total_return_amount": 82590,
        "profit_exits": 1,
        "loss_exits": 2,
        "close_exits": 2,
        "results": [
          {
            "code": "006340",
            "name": "대원전선",
            "entry_price": 10100,
            "exit_price": 9797,
            "quantity": 276,
            "return_pct": -3.0,
            "return_amount": -83628,
            "exit_type": "loss",
            "entry_time": "09:05",
            "exit_time": "09:08",
            "high_price": 0,
            "low_price": 0,
            "max_profit_pct": 4.75,
            "max_loss_pct": -4.26
          },
          {
            "code": "289930",
            "name": "웨이비스",
            "entry_price": 22750,
            "exit_price": 23887,
            "quantity": 122,
            "return_pct": 5.0,
            "return_amount": 138714,
            "exit_type": "profit",
            "entry_time": "09:05",
            "exit_time": "09:22",
            "high_price": 0,
            "low_price": 0,
            "max_profit_pct": 7.69,
            "max_loss_pct": 0
          },
          {
            "code": "089030",
            "name": "테크윙",
            "entry_price": 60700,
            "exit_price": 62100,
            "quantity": 45,
            "return_pct": 2.31,
            "return_amount": 63000,
            "exit_type": "close",
            "entry_time": "09:05",
            "exit_time": "15:20",
            "high_price": 0,
            "low_price": 0,
            "max_profit_pct": 2.97,
            "max_loss_pct": -0.16
          },
          {
            "code": "232140",
            "name": "와이씨",
            "entry_price": 23050,
            "exit_price": 23450,
            "quantity": 120,
            "return_pct": 1.74,
            "return_amount": 48000,
            "exit_type": "close",
            "entry_time": "09:05",
            "exit_time": "15:20",
            "high_price": 0,
            "low_price": 0,
            "max_profit_pct": 3.47,
            "max_loss_pct": -1.95
          },
          {
            "code": "019210",
            "name": "와이지-원",
            "entry_price": 16560,
            "exit_price": 16063,
            "quantity": 168,
            "return_pct": -3.0,
            "return_amount": -83496,
            "exit_type": "loss",
            "entry_time": "09:05",
            "exit_time": "10:18",
            "high_price": 0,
            "low_price": 0,
            "max_profit_pct": 1.33,
            "max_loss_pct": -3.44
          }
        ]
      }
    },
    "team_c": {
      "team_id": "team_c",
      "team_name": "Gamma Disclosure",
      "strategy_id": "dart_disclosure",
      "status": "success",
      "selection": {
        "strategy_id": "dart_disclosure",
        "strategy_name": "DART 공시",
        "date": "20260424",
        "selected_at": "2026-04-27 18:30:53",
        "count": 2,
        "candidates": [
          {
            "code": "394800",
            "name": "쓰리빌리언",
            "price": 13930,
            "change_pct": 11.35,
            "score": 75.6,
            "score_detail": {
              "disclosure": 20.0,
              "change_pct": 25,
              "trading_value": 20.0,
              "market_cap": 10.61849665632,
              "dart_raw": 15.0,
              "disclosures": [
                {
                  "category": "투자",
                  "report_nm": "주요사항보고서(유상증자결정)",
                  "amount": 0
                }
              ]
            },
            "rank": 1,
            "market_cap": 442437360680,
            "volume": 1009738,
            "trading_value": 13915627640
          },
          {
            "code": "412350",
            "name": "레이저쎌",
            "price": 7720,
            "change_pct": -0.52,
            "score": 48.3,
            "score_detail": {
              "disclosure": 40.0,
              "change_pct": 0,
              "trading_value": 5.796076927795691,
              "market_cap": 2.47160203488,
              "dart_raw": 30,
              "disclosures": [
                {
                  "category": "계약",
                  "report_nm": "단일판매ㆍ공급계약체결              ",
                  "amount": 0
                }
              ]
            },
            "rank": 2,
            "market_cap": 102983418120,
            "volume": 511942,
            "trading_value": 4032802415
          }
        ],
        "params": {
          "weights": {
            "disclosure": 40,
            "change_pct": 25,
            "trading_value": 20,
            "market_cap": 15
          },
          "min_market_cap": 100000000000,
          "max_market_cap": 10000000000000,
          "min_trading_value": 1000000000
        },
        "simulation": null
      },
      "simulation": {
        "date": "20260427",
        "strategy_id": "dart_disclosure",
        "strategy_name": "Gamma Disclosure",
        "total_trades": 2,
        "wins": 1,
        "losses": 1,
        "win_rate": 50.0,
        "total_return": 2.0,
        "avg_return": 1.0,
        "total_return_amount": 102771,
        "profit_exits": 1,
        "loss_exits": 1,
        "close_exits": 0,
        "results": [
          {
            "code": "394800",
            "name": "쓰리빌리언",
            "entry_price": 13680,
            "exit_price": 13269,
            "quantity": 376,
            "return_pct": -3.0,
            "return_amount": -154536,
            "exit_type": "loss",
            "entry_time": "09:05",
            "exit_time": "10:21",
            "high_price": 0,
            "low_price": 0,
            "max_profit_pct": 0.15,
            "max_loss_pct": -5.92
          },
          {
            "code": "412350",
            "name": "레이저쎌",
            "entry_price": 8620,
            "exit_price": 9051,
            "quantity": 597,
            "return_pct": 5.0,
            "return_amount": 257307,
            "exit_type": "profit",
            "entry_time": "09:05",
            "exit_time": "09:08",
            "high_price": 0,
            "low_price": 0,
            "max_profit_pct": 5.34,
            "max_loss_pct": -3.13
          }
        ]
      }
    },
    "team_d": {
      "team_id": "team_d",
      "team_name": "Delta Theme",
      "strategy_id": "theme_policy",
      "status": "success",
      "selection": {
        "strategy_id": "theme_policy",
        "strategy_name": "테마/정책",
        "date": "20260424",
        "selected_at": "2026-04-27 18:30:51",
        "count": 5,
        "candidates": [
          {
            "code": "373220",
            "name": "LG에너지솔루션",
            "price": 464000,
            "change_pct": -3.53,
            "score": 77.4,
            "score_detail": {
              "theme_relevance": 40.0,
              "change_pct": 2.4,
              "trading_value": 20.0,
              "theme_strength": 15.0,
              "themes": [
                "기계·장비",
                "코스닥 150 정보기술",
                "코스닥 150 필수소비재",
                "일반서비스",
                "기계·장비",
                "화학",
                "코스닥 150 소재",
                "의료·정밀기기",
                "비금속",
                "금속"
              ]
            },
            "rank": 1,
            "market_cap": 0,
            "volume": 500,
            "trading_value": 1085760000000
          },
          {
            "code": "034020",
            "name": "두산에너빌리티",
            "price": 128900,
            "change_pct": 1.42,
            "score": 73.8,
            "score_detail": {
              "theme_relevance": 40.0,
              "change_pct": 3.5,
              "trading_value": 15.2,
              "theme_strength": 15.0,
              "themes": [
                "기계·장비",
                "코스닥 150 정보기술",
                "코스닥 150 필수소비재",
                "일반서비스",
                "기계·장비",
                "화학",
                "코스닥 150 소재",
                "의료·정밀기기",
                "비금속",
                "금속"
              ]
            },
            "rank": 2,
            "market_cap": 0,
            "volume": 5000,
            "trading_value": 825683000000
          },
          {
            "code": "012450",
            "name": "한화에어로스페이스",
            "price": 1454000,
            "change_pct": -0.62,
            "score": 72.3,
            "score_detail": {
              "theme_relevance": 40.0,
              "change_pct": 3.5,
              "trading_value": 13.8,
              "theme_strength": 15.0,
              "themes": [
                "기계·장비",
                "코스닥 150 정보기술",
                "코스닥 150 필수소비재",
                "일반서비스",
                "기계·장비",
                "화학",
                "코스닥 150 소재",
                "의료·정밀기기",
                "비금속",
                "금속"
              ]
            },
            "rank": 3,
            "market_cap": 0,
            "volume": 5000,
            "trading_value": 749732000000
          },
          {
            "code": "329180",
            "name": "HD현대중공업",
            "price": 673000,
            "change_pct": 0.3,
            "score": 68.8,
            "score_detail": {
              "theme_relevance": 40.0,
              "change_pct": 0.8,
              "trading_value": 13.0,
              "theme_strength": 15.0,
              "themes": [
                "기계·장비",
                "코스닥 150 정보기술",
                "코스닥 150 필수소비재",
                "일반서비스",
                "기계·장비",
                "화학",
                "코스닥 150 소재",
                "의료·정밀기기",
                "비금속",
                "금속"
              ]
            },
            "rank": 4,
            "market_cap": 0,
            "volume": 5000,
            "trading_value": 706389000000
          },
          {
            "code": "009150",
            "name": "삼성전기",
            "price": 794000,
            "change_pct": 0.76,
            "score": 67.8,
            "score_detail": {
              "theme_relevance": 40.0,
              "change_pct": 1.9,
              "trading_value": 10.9,
              "theme_strength": 15.0,
              "themes": [
                "기계·장비",
                "코스닥 150 정보기술",
                "코스닥 150 필수소비재",
                "일반서비스",
                "기계·장비",
                "화학",
                "코스닥 150 소재",
                "의료·정밀기기",
                "비금속",
                "금속"
              ]
            },
            "rank": 5,
            "market_cap": 0,
            "volume": 5000,
            "trading_value": 593068000000
          }
        ],
        "params": {
          "active_themes": [
            {
              "name": "기계·장비",
              "change_pct": 4.44
            },
            {
              "name": "코스닥 150 정보기술",
              "change_pct": 4.27
            },
            {
              "name": "코스닥 150 필수소비재",
              "change_pct": 4.09
            },
            {
              "name": "일반서비스",
              "change_pct": 3.85
            },
            {
              "name": "기계·장비",
              "change_pct": 3.44
            },
            {
              "name": "화학",
              "change_pct": 3.36
            },
            {
              "name": "코스닥 150 소재",
              "change_pct": 3.3
            },
            {
              "name": "의료·정밀기기",
              "change_pct": 3.18
            },
            {
              "name": "비금속",
              "change_pct": 3.13
            },
            {
              "name": "금속",
              "change_pct": 3.08
            }
          ],
          "theme_count": 10,
          "total_stocks": 72,
          "weights": {
            "theme_relevance": 40,
            "change_pct": 25,
            "trading_value": 20,
            "theme_strength": 15
          }
        },
        "simulation": null
      },
      "simulation": {
        "date": "20260427",
        "strategy_id": "theme_policy",
        "strategy_name": "Delta Theme",
        "total_trades": 5,
        "wins": 2,
        "losses": 3,
        "win_rate": 40.0,
        "total_return": 0.82,
        "avg_return": 0.16,
        "total_return_amount": 16100,
        "profit_exits": 0,
        "loss_exits": 0,
        "close_exits": 5,
        "results": [
          {
            "code": "373220",
            "name": "LG에너지솔루션",
            "entry_price": 473500,
            "exit_price": 464000,
            "quantity": 4,
            "return_pct": -2.01,
            "return_amount": -38000,
            "exit_type": "close",
            "entry_time": "09:05",
            "exit_time": "15:20",
            "high_price": 0,
            "low_price": 0,
            "max_profit_pct": 0,
            "max_loss_pct": -2.64
          },
          {
            "code": "034020",
            "name": "두산에너빌리티",
            "entry_price": 126600,
            "exit_price": 128900,
            "quantity": 17,
            "return_pct": 1.82,
            "return_amount": 39100,
            "exit_type": "close",
            "entry_time": "09:05",
            "exit_time": "15:20",
            "high_price": 0,
            "low_price": 0,
            "max_profit_pct": 2.13,
            "max_loss_pct": -0.71
          },
          {
            "code": "012450",
            "name": "한화에어로스페이스",
            "entry_price": 1461000,
            "exit_price": 1454000,
            "quantity": 1,
            "return_pct": -0.48,
            "return_amount": -7000,
            "exit_type": "close",
            "entry_time": "09:05",
            "exit_time": "15:20",
            "high_price": 0,
            "low_price": 0,
            "max_profit_pct": 0.21,
            "max_loss_pct": -1.3
          },
          {
            "code": "329180",
            "name": "HD현대중공업",
            "entry_price": 675000,
            "exit_price": 673000,
            "quantity": 3,
            "return_pct": -0.3,
            "return_amount": -6000,
            "exit_type": "close",
            "entry_time": "09:05",
            "exit_time": "15:20",
            "high_price": 0,
            "low_price": 0,
            "max_profit_pct": 2.07,
            "max_loss_pct": -1.63
          },
          {
            "code": "009150",
            "name": "삼성전기",
            "entry_price": 780000,
            "exit_price": 794000,
            "quantity": 2,
            "return_pct": 1.79,
            "return_amount": 28000,
            "exit_type": "close",
            "entry_time": "09:05",
            "exit_time": "15:20",
            "high_price": 0,
            "low_price": 0,
            "max_profit_pct": 1.92,
            "max_loss_pct": -0.77
          }
        ]
      }
    },
    "team_e": {
      "team_id": "team_e",
      "team_name": "Echo Frontier",
      "strategy_id": "frontier_gap",
      "status": "success",
      "selection": {
        "strategy_id": "frontier_gap",
        "strategy_name": "프론티어 갭",
        "date": "20260424",
        "selected_at": "2026-04-27 18:31:01",
        "count": 5,
        "candidates": [
          {
            "code": "214420",
            "name": "토니모리",
            "price": 7500,
            "change_pct": 4.748603351955307,
            "score": 69.3,
            "score_detail": {
              "gap_pct": 40.0,
              "volume_surge": 18.503900871959615,
              "trading_value": 0.7682865162745148,
              "price_level": 10
            },
            "rank": 1,
            "market_cap": 181373184460,
            "volume": 1362633,
            "trading_value": 10428548940
          },
          {
            "code": "308080",
            "name": "바이젠셀",
            "price": 9980,
            "change_pct": 3.958333333333333,
            "score": 63.7,
            "score_detail": {
              "gap_pct": 33.34313725490196,
              "volume_surge": 9.942634235888022,
              "trading_value": 10.437479834200502,
              "price_level": 10
            },
            "rank": 2,
            "market_cap": 229591712000,
            "volume": 13234845,
            "trading_value": 141676011430
          },
          {
            "code": "003350",
            "name": "한국화장품제조",
            "price": 10100,
            "change_pct": 3.909465020576132,
            "score": 59.3,
            "score_detail": {
              "gap_pct": 32.93149358508836,
              "volume_surge": 15.419917393299679,
              "trading_value": 0.9576127147065228,
              "price_level": 10
            },
            "rank": 3,
            "market_cap": 232944800000,
            "volume": 1232723,
            "trading_value": 12998420315
          },
          {
            "code": "014620",
            "name": "성광벤드",
            "price": 41150,
            "change_pct": 3.0037546933667083,
            "score": 58.5,
            "score_detail": {
              "gap_pct": 25.302216005300746,
              "volume_surge": 16.126663607159248,
              "trading_value": 7.065223622976356,
              "price_level": 10
            },
            "rank": 4,
            "market_cap": 1262802658200,
            "volume": 2074374,
            "trading_value": 95901761600
          },
          {
            "code": "067990",
            "name": "도이치모터스",
            "price": 4630,
            "change_pct": 2.0948180815876514,
            "score": 58.2,
            "score_detail": {
              "gap_pct": 17.6457617225501,
              "volume_surge": 35.0,
              "trading_value": 0.5774638986247175,
              "price_level": 5.0
            },
            "rank": 5,
            "market_cap": 144448672500,
            "volume": 1591524,
            "trading_value": 7838365506
          }
        ],
        "params": {
          "gap_min": 2.0,
          "gap_max": 5.0,
          "min_price": 3000,
          "min_trading_value": 50,
          "volume_surge_mult": 2.0,
          "weights": {
            "gap_pct": 40,
            "volume_surge": 35,
            "trading_value": 15,
            "price_level": 10
          }
        },
        "simulation": null
      },
      "simulation": {
        "date": "20260427",
        "strategy_id": "frontier_gap",
        "strategy_name": "Echo Frontier",
        "total_trades": 5,
        "wins": 5,
        "losses": 0,
        "win_rate": 100.0,
        "total_return": 19.43,
        "avg_return": 3.89,
        "total_return_amount": 403308,
        "profit_exits": 3,
        "loss_exits": 0,
        "close_exits": 2,
        "results": [
          {
            "code": "214420",
            "name": "토니모리",
            "entry_price": 7610,
            "exit_price": 7750,
            "quantity": 274,
            "return_pct": 1.84,
            "return_amount": 38360,
            "exit_type": "close",
            "entry_time": "09:05",
            "exit_time": "15:20",
            "high_price": 0,
            "low_price": 0,
            "max_profit_pct": 4.07,
            "max_loss_pct": -1.05
          },
          {
            "code": "308080",
            "name": "바이젠셀",
            "entry_price": 11020,
            "exit_price": 11571,
            "quantity": 189,
            "return_pct": 5.0,
            "return_amount": 104139,
            "exit_type": "profit",
            "entry_time": "09:05",
            "exit_time": "09:07",
            "high_price": 0,
            "low_price": 0,
            "max_profit_pct": 12.25,
            "max_loss_pct": 0
          },
          {
            "code": "003350",
            "name": "한국화장품제조",
            "entry_price": 10390,
            "exit_price": 10660,
            "quantity": 200,
            "return_pct": 2.6,
            "return_amount": 54000,
            "exit_type": "close",
            "entry_time": "09:05",
            "exit_time": "15:20",
            "high_price": 0,
            "low_price": 0,
            "max_profit_pct": 3.66,
            "max_loss_pct": -0.29
          },
          {
            "code": "014620",
            "name": "성광벤드",
            "entry_price": 45700,
            "exit_price": 47985,
            "quantity": 45,
            "return_pct": 5.0,
            "return_amount": 102825,
            "exit_type": "profit",
            "entry_time": "09:05",
            "exit_time": "13:16",
            "high_price": 0,
            "low_price": 0,
            "max_profit_pct": 6.89,
            "max_loss_pct": -0.22
          },
          {
            "code": "067990",
            "name": "도이치모터스",
            "entry_price": 5370,
            "exit_price": 5638,
            "quantity": 388,
            "return_pct": 4.99,
            "return_amount": 103984,
            "exit_type": "profit",
            "entry_time": "09:05",
            "exit_time": "09:43",
            "high_price": 0,
            "low_price": 0,
            "max_profit_pct": 5.77,
            "max_loss_pct": -2.05
          }
        ]
      }
    },
    "team_i": {
      "team_id": "team_i",
      "team_name": "Alpha-Delta Hybrid",
      "strategy_id": "hybrid_alpha_delta",
      "status": "success",
      "selection": {
        "strategy_id": "hybrid_alpha_delta",
        "strategy_name": "Alpha-Delta 하이브리드",
        "date": "20260424",
        "selected_at": "2026-04-27 18:32:21",
        "count": 5,
        "candidates": [
          {
            "code": "006340",
            "name": "대원전선",
            "price": 9020,
            "change_pct": 10.81,
            "score": 65.0,
            "score_detail": {
              "alpha_score": 91.3,
              "delta_score": 0.0,
              "alpha_norm": 100.0,
              "delta_norm": 0.0,
              "alpha_weighted": 65.0,
              "delta_weighted": 0.0,
              "overlap_bonus": 0,
              "source": [
                "alpha"
              ]
            },
            "rank": 1,
            "market_cap": 0,
            "volume": 116448411,
            "trading_value": 1033431895775
          },
          {
            "code": "289930",
            "name": "웨이비스",
            "price": 22600,
            "change_pct": 13.0,
            "score": 48.1,
            "score_detail": {
              "alpha_score": 67.6,
              "delta_score": 0.0,
              "alpha_norm": 74.0,
              "delta_norm": 0.0,
              "alpha_weighted": 48.1,
              "delta_weighted": 0.0,
              "overlap_bonus": 0,
              "source": [
                "alpha"
              ]
            },
            "rank": 2,
            "market_cap": 0,
            "volume": 1611419,
            "trading_value": 36439230050
          },
          {
            "code": "089030",
            "name": "테크윙",
            "price": 61800,
            "change_pct": 12.36,
            "score": 47.1,
            "score_detail": {
              "alpha_score": 66.2,
              "delta_score": 0.0,
              "alpha_norm": 72.5,
              "delta_norm": 0.0,
              "alpha_weighted": 47.1,
              "delta_weighted": 0.0,
              "overlap_bonus": 0,
              "source": [
                "alpha"
              ]
            },
            "rank": 3,
            "market_cap": 0,
            "volume": 4983557,
            "trading_value": 300623364950
          },
          {
            "code": "373220",
            "name": "LG에너지솔루션",
            "price": 464000,
            "change_pct": -3.53,
            "score": 35.0,
            "score_detail": {
              "alpha_score": 0.0,
              "delta_score": 77.4,
              "alpha_norm": 0.0,
              "delta_norm": 100.0,
              "alpha_weighted": 0.0,
              "delta_weighted": 35.0,
              "overlap_bonus": 0,
              "source": [
                "delta"
              ]
            },
            "rank": 4,
            "market_cap": 0,
            "volume": 500,
            "trading_value": 1085760000000
          },
          {
            "code": "034020",
            "name": "두산에너빌리티",
            "price": 128900,
            "change_pct": 1.42,
            "score": 33.4,
            "score_detail": {
              "alpha_score": 0.0,
              "delta_score": 73.8,
              "alpha_norm": 0.0,
              "delta_norm": 95.3,
              "alpha_weighted": 0.0,
              "delta_weighted": 33.4,
              "overlap_bonus": 0,
              "source": [
                "delta"
              ]
            },
            "rank": 5,
            "market_cap": 0,
            "volume": 5000,
            "trading_value": 825683000000
          }
        ],
        "params": {
          "weight_alpha": 0.65,
          "weight_delta": 0.35,
          "overlap_bonus": 10.0,
          "sub_top_n": 10,
          "alpha_slot": 3,
          "delta_slot": 2,
          "score_normalization": "min-max per-strategy (0~100)",
          "alpha_strategy": "momentum",
          "delta_strategy": "theme_policy"
        },
        "simulation": null
      },
      "simulation": {
        "date": "20260427",
        "strategy_id": "hybrid_alpha_delta",
        "strategy_name": "Alpha-Delta Hybrid",
        "total_trades": 5,
        "wins": 3,
        "losses": 2,
        "win_rate": 60.0,
        "total_return": 4.12,
        "avg_return": 0.82,
        "total_return_amount": 82459,
        "profit_exits": 1,
        "loss_exits": 1,
        "close_exits": 3,
        "results": [
          {
            "code": "006340",
            "name": "대원전선",
            "entry_price": 10100,
            "exit_price": 9797,
            "quantity": 199,
            "return_pct": -3.0,
            "return_amount": -60297,
            "exit_type": "loss",
            "entry_time": "09:05",
            "exit_time": "09:08",
            "high_price": 0,
            "low_price": 0,
            "max_profit_pct": 4.75,
            "max_loss_pct": -4.26
          },
          {
            "code": "289930",
            "name": "웨이비스",
            "entry_price": 22750,
            "exit_price": 23887,
            "quantity": 88,
            "return_pct": 5.0,
            "return_amount": 100056,
            "exit_type": "profit",
            "entry_time": "09:05",
            "exit_time": "09:22",
            "high_price": 0,
            "low_price": 0,
            "max_profit_pct": 7.69,
            "max_loss_pct": 0
          },
          {
            "code": "089030",
            "name": "테크윙",
            "entry_price": 60700,
            "exit_price": 62100,
            "quantity": 33,
            "return_pct": 2.31,
            "return_amount": 46200,
            "exit_type": "close",
            "entry_time": "09:05",
            "exit_time": "15:20",
            "high_price": 0,
            "low_price": 0,
            "max_profit_pct": 2.97,
            "max_loss_pct": -0.16
          },
          {
            "code": "373220",
            "name": "LG에너지솔루션",
            "entry_price": 473500,
            "exit_price": 464000,
            "quantity": 4,
            "return_pct": -2.01,
            "return_amount": -38000,
            "exit_type": "close",
            "entry_time": "09:05",
            "exit_time": "15:20",
            "high_price": 0,
            "low_price": 0,
            "max_profit_pct": 0,
            "max_loss_pct": -2.64
          },
          {
            "code": "034020",
            "name": "두산에너빌리티",
            "entry_price": 126600,
            "exit_price": 128900,
            "quantity": 15,
            "return_pct": 1.82,
            "return_amount": 34500,
            "exit_type": "close",
            "entry_time": "09:05",
            "exit_time": "15:20",
            "high_price": 0,
            "low_price": 0,
            "max_profit_pct": 2.13,
            "max_loss_pct": -0.71
          }
        ]
      }
    },
    "team_f": {
      "team_id": "team_f",
      "team_name": "Zeta Volatility",
      "strategy_id": "volatility_breakout_lw",
      "status": "success",
      "selection": {
        "strategy_id": "volatility_breakout_lw",
        "strategy_name": "변동성 돌파 (Larry Williams)",
        "date": "20260424",
        "selected_at": "2026-04-27 18:32:21",
        "count": 5,
        "candidates": [
          {
            "code": "098460",
            "name": "고영",
            "price": 42300,
            "change_pct": 29.95,
            "score": 65.47,
            "score_detail": {
              "breakout_strength": 33.24,
              "volume_surge": 7.23,
              "trading_value": 15.0,
              "price_level": 10
            },
            "rank": 1,
            "market_cap": 2904096136500,
            "volume": 30620110,
            "trading_value": 1220846305975
          },
          {
            "code": "172670",
            "name": "에이엘티",
            "price": 15910,
            "change_pct": 26.27,
            "score": 64.94,
            "score_detail": {
              "breakout_strength": 44.59,
              "volume_surge": 10.05,
              "trading_value": 0.3,
              "price_level": 10
            },
            "rank": 2,
            "market_cap": 142557720690,
            "volume": 1613327,
            "trading_value": 24188539920
          },
          {
            "code": "080220",
            "name": "제주반도체",
            "price": 54000,
            "change_pct": 18.16,
            "score": 62.42,
            "score_detail": {
              "breakout_strength": 33.17,
              "volume_surge": 5.77,
              "trading_value": 13.48,
              "price_level": 10
            },
            "rank": 3,
            "market_cap": 1859912982000,
            "volume": 20601605,
            "trading_value": 1096993357950
          },
          {
            "code": "036540",
            "name": "SFA반도체",
            "price": 9640,
            "change_pct": 22.18,
            "score": 62.11,
            "score_detail": {
              "breakout_strength": 42.16,
              "volume_surge": 4.51,
              "trading_value": 5.43,
              "price_level": 10
            },
            "rank": 4,
            "market_cap": 1585397320920,
            "volume": 47485150,
            "trading_value": 442254901570
          },
          {
            "code": "123690",
            "name": "한국화장품",
            "price": 9000,
            "change_pct": 7.4,
            "score": 61.45,
            "score_detail": {
              "breakout_strength": 20.98,
              "volume_surge": 30.0,
              "trading_value": 0.47,
              "price_level": 10
            },
            "rank": 5,
            "market_cap": 144612000000,
            "volume": 3978509,
            "trading_value": 37908427415
          }
        ],
        "params": {
          "k_value": 0.5,
          "min_price": 3000,
          "min_trading_value": 5000000000,
          "min_market_cap": 50000000000,
          "volume_surge_min": 1.5,
          "weights": {
            "breakout_strength": 45,
            "volume_surge": 30,
            "trading_value": 15,
            "price_level": 10
          }
        },
        "simulation": null
      },
      "simulation": {
        "date": "20260427",
        "strategy_id": "volatility_breakout_lw",
        "strategy_name": "Zeta Volatility",
        "total_trades": 5,
        "wins": 2,
        "losses": 3,
        "win_rate": 40.0,
        "total_return": -2.99,
        "avg_return": -0.6,
        "total_return_amount": -58182,
        "profit_exits": 1,
        "loss_exits": 3,
        "close_exits": 1,
        "results": [
          {
            "code": "098460",
            "name": "고영",
            "entry_price": 44200,
            "exit_price": 42874,
            "quantity": 44,
            "return_pct": -3.0,
            "return_amount": -58344,
            "exit_type": "loss",
            "entry_time": "09:05",
            "exit_time": "09:52",
            "high_price": 0,
            "low_price": 0,
            "max_profit_pct": 1.24,
            "max_loss_pct": -4.07
          },
          {
            "code": "172670",
            "name": "에이엘티",
            "entry_price": 17990,
            "exit_price": 17450,
            "quantity": 110,
            "return_pct": -3.0,
            "return_amount": -59400,
            "exit_type": "loss",
            "entry_time": "09:05",
            "exit_time": "09:15",
            "high_price": 0,
            "low_price": 0,
            "max_profit_pct": 4.17,
            "max_loss_pct": -7.34
          },
          {
            "code": "080220",
            "name": "제주반도체",
            "entry_price": 54900,
            "exit_price": 57645,
            "quantity": 36,
            "return_pct": 5.0,
            "return_amount": 98820,
            "exit_type": "profit",
            "entry_time": "09:05",
            "exit_time": "11:56",
            "high_price": 0,
            "low_price": 0,
            "max_profit_pct": 13.3,
            "max_loss_pct": -1.28
          },
          {
            "code": "036540",
            "name": "SFA반도체",
            "entry_price": 10270,
            "exit_price": 9961,
            "quantity": 192,
            "return_pct": -3.01,
            "return_amount": -59328,
            "exit_type": "loss",
            "entry_time": "09:05",
            "exit_time": "09:31",
            "high_price": 0,
            "low_price": 0,
            "max_profit_pct": 1.56,
            "max_loss_pct": -5.26
          },
          {
            "code": "123690",
            "name": "한국화장품",
            "entry_price": 8850,
            "exit_price": 8940,
            "quantity": 223,
            "return_pct": 1.02,
            "return_amount": 20070,
            "exit_type": "close",
            "entry_time": "09:05",
            "exit_time": "15:20",
            "high_price": 0,
            "low_price": 0,
            "max_profit_pct": 2.26,
            "max_loss_pct": 0
          }
        ]
      }
    },
    "team_h": {
      "team_id": "team_h",
      "team_name": "Theta Sector",
      "strategy_id": "sector_rotation",
      "status": "success",
      "selection": {
        "strategy_id": "sector_rotation",
        "strategy_name": "섹터 로테이션 (KOSPI 업종)",
        "date": "20260424",
        "selected_at": "2026-04-27 18:32:21",
        "count": 5,
        "candidates": [
          {
            "code": "034020",
            "name": "두산에너빌리티",
            "price": 127100,
            "change_pct": 3.67,
            "score": 74.31,
            "score_detail": {
              "sector_strength": 35,
              "stock_momentum": 9.85,
              "market_cap_rank": 14.47,
              "volume_surge": 15.0
            },
            "rank": 1,
            "market_cap": 81415321656600,
            "volume": 5682618,
            "trading_value": 713727129050
          },
          {
            "code": "443060",
            "name": "HD현대마린솔루션",
            "price": 253500,
            "change_pct": 11.18,
            "score": 70.23,
            "score_detail": {
              "sector_strength": 35,
              "stock_momentum": 30.0,
              "market_cap_rank": 2.02,
              "volume_surge": 3.21
            },
            "rank": 2,
            "market_cap": 11365282110000,
            "volume": 627159,
            "trading_value": 152687791500
          },
          {
            "code": "373220",
            "name": "LG에너지솔루션",
            "price": 481000,
            "change_pct": 3.11,
            "score": 67.37,
            "score_detail": {
              "sector_strength": 35,
              "stock_momentum": 8.35,
              "market_cap_rank": 20.0,
              "volume_surge": 4.03
            },
            "rank": 3,
            "market_cap": 112554000000000,
            "volume": 402718,
            "trading_value": 191711449500
          },
          {
            "code": "010120",
            "name": "LS ELECTRIC",
            "price": 226500,
            "change_pct": 4.38,
            "score": 60.88,
            "score_detail": {
              "sector_strength": 35,
              "stock_momentum": 11.75,
              "market_cap_rank": 6.04,
              "volume_surge": 8.09
            },
            "rank": 4,
            "market_cap": 33975000000000,
            "volume": 1695903,
            "trading_value": 385028377250
          },
          {
            "code": "006260",
            "name": "LS",
            "price": 398500,
            "change_pct": 6.55,
            "score": 56.63,
            "score_detail": {
              "sector_strength": 35,
              "stock_momentum": 17.58,
              "market_cap_rank": 2.21,
              "volume_surge": 1.84
            },
            "rank": 5,
            "market_cap": 12433200000000,
            "volume": 223625,
            "trading_value": 87557616750
          }
        ],
        "params": {
          "top_sectors": 5,
          "stocks_per_sector": 3,
          "min_price": 3000,
          "min_market_cap": 100000000000,
          "min_trading_value": 5000000000,
          "min_change_pct": 0.5,
          "weights": {
            "sector_strength": 35,
            "stock_momentum": 30,
            "market_cap_rank": 20,
            "volume_surge": 15
          }
        },
        "simulation": null
      },
      "simulation": {
        "date": "20260427",
        "strategy_id": "sector_rotation",
        "strategy_name": "Theta Sector",
        "total_trades": 5,
        "wins": 4,
        "losses": 1,
        "win_rate": 80.0,
        "total_return": 8.11,
        "avg_return": 1.62,
        "total_return_amount": 152600,
        "profit_exits": 1,
        "loss_exits": 0,
        "close_exits": 4,
        "results": [
          {
            "code": "034020",
            "name": "두산에너빌리티",
            "entry_price": 126600,
            "exit_price": 128900,
            "quantity": 15,
            "return_pct": 1.82,
            "return_amount": 34500,
            "exit_type": "close",
            "entry_time": "09:05",
            "exit_time": "15:20",
            "high_price": 0,
            "low_price": 0,
            "max_profit_pct": 2.13,
            "max_loss_pct": -0.71
          },
          {
            "code": "443060",
            "name": "HD현대마린솔루션",
            "entry_price": 277000,
            "exit_price": 280500,
            "quantity": 7,
            "return_pct": 1.26,
            "return_amount": 24500,
            "exit_type": "close",
            "entry_time": "09:05",
            "exit_time": "15:20",
            "high_price": 0,
            "low_price": 0,
            "max_profit_pct": 3.43,
            "max_loss_pct": -1.62
          },
          {
            "code": "373220",
            "name": "LG에너지솔루션",
            "entry_price": 473500,
            "exit_price": 464000,
            "quantity": 4,
            "return_pct": -2.01,
            "return_amount": -38000,
            "exit_type": "close",
            "entry_time": "09:05",
            "exit_time": "15:20",
            "high_price": 0,
            "low_price": 0,
            "max_profit_pct": 0,
            "max_loss_pct": -2.64
          },
          {
            "code": "010120",
            "name": "LS ELECTRIC",
            "entry_price": 244000,
            "exit_price": 256200,
            "quantity": 8,
            "return_pct": 5.0,
            "return_amount": 97600,
            "exit_type": "profit",
            "entry_time": "09:05",
            "exit_time": "11:25",
            "high_price": 0,
            "low_price": 0,
            "max_profit_pct": 6.97,
            "max_loss_pct": -1.02
          },
          {
            "code": "006260",
            "name": "LS",
            "entry_price": 417500,
            "exit_price": 426000,
            "quantity": 4,
            "return_pct": 2.04,
            "return_amount": 34000,
            "exit_type": "close",
            "entry_time": "09:05",
            "exit_time": "15:20",
            "high_price": 0,
            "low_price": 0,
            "max_profit_pct": 4.79,
            "max_loss_pct": 0
          }
        ]
      }
    },
    "team_g": {
      "team_id": "team_g",
      "team_name": "Kappa Turtle",
      "strategy_id": "turtle_breakout_short",
      "status": "success",
      "selection": {
        "strategy_id": "turtle_breakout_short",
        "strategy_name": "단축 터틀 돌파 (5/10일 신고가)",
        "date": "20260424",
        "selected_at": "2026-04-27 18:32:22",
        "count": 5,
        "candidates": [
          {
            "code": "439090",
            "name": "마녀공장",
            "price": 16390,
            "change_pct": 22.96,
            "score": 76.31,
            "score_detail": {
              "breakout_freshness": 34.12,
              "volume_surge": 30.0,
              "trading_value": 0.7,
              "price_momentum": 11.5
            },
            "rank": 1,
            "market_cap": 268685531400,
            "volume": 2663328,
            "trading_value": 42869551295
          },
          {
            "code": "098460",
            "name": "고영",
            "price": 42300,
            "change_pct": 29.95,
            "score": 65.32,
            "score_detail": {
              "breakout_freshness": 27.64,
              "volume_surge": 2.68,
              "trading_value": 20.0,
              "price_momentum": 14.99
            },
            "rank": 2,
            "market_cap": 2904096136500,
            "volume": 30620110,
            "trading_value": 1220846305975
          },
          {
            "code": "027360",
            "name": "아주IB투자",
            "price": 18720,
            "change_pct": 28.31,
            "score": 54.98,
            "score_detail": {
              "breakout_freshness": 29.45,
              "volume_surge": 0.7,
              "trading_value": 10.65,
              "price_momentum": 14.17
            },
            "rank": 3,
            "market_cap": 2267842000320,
            "volume": 37202942,
            "trading_value": 650227037855
          },
          {
            "code": "036540",
            "name": "SFA반도체",
            "price": 9640,
            "change_pct": 22.18,
            "score": 53.33,
            "score_detail": {
              "breakout_freshness": 30.88,
              "volume_surge": 4.09,
              "trading_value": 7.25,
              "price_momentum": 11.1
            },
            "rank": 4,
            "market_cap": 1585397320920,
            "volume": 47485150,
            "trading_value": 442254901570
          },
          {
            "code": "123690",
            "name": "한국화장품",
            "price": 9000,
            "change_pct": 7.4,
            "score": 53.16,
            "score_detail": {
              "breakout_freshness": 23.28,
              "volume_surge": 25.55,
              "trading_value": 0.62,
              "price_momentum": 3.7
            },
            "rank": 5,
            "market_cap": 144612000000,
            "volume": 3978509,
            "trading_value": 37908427415
          }
        ],
        "params": {
          "lookback_days": 5,
          "history_fetch_days": 14,
          "min_price": 3000,
          "min_market_cap": 100000000000,
          "min_trading_value": 5000000000,
          "volume_surge_min": 1.5,
          "min_price_increase": 1.0,
          "weights": {
            "breakout_freshness": 35,
            "volume_surge": 30,
            "trading_value": 20,
            "price_momentum": 15
          }
        },
        "simulation": null
      },
      "simulation": {
        "date": "20260427",
        "strategy_id": "turtle_breakout_short",
        "strategy_name": "Kappa Turtle",
        "total_trades": 5,
        "wins": 2,
        "losses": 3,
        "win_rate": 40.0,
        "total_return": -7.47,
        "avg_return": -1.49,
        "total_return_amount": -149233,
        "profit_exits": 0,
        "loss_exits": 3,
        "close_exits": 2,
        "results": [
          {
            "code": "439090",
            "name": "마녀공장",
            "entry_price": 15400,
            "exit_price": 15480,
            "quantity": 130,
            "return_pct": 0.52,
            "return_amount": 10400,
            "exit_type": "close",
            "entry_time": "09:05",
            "exit_time": "15:20",
            "high_price": 0,
            "low_price": 0,
            "max_profit_pct": 1.23,
            "max_loss_pct": -0.32
          },
          {
            "code": "098460",
            "name": "고영",
            "entry_price": 44200,
            "exit_price": 42874,
            "quantity": 45,
            "return_pct": -3.0,
            "return_amount": -59670,
            "exit_type": "loss",
            "entry_time": "09:05",
            "exit_time": "09:52",
            "high_price": 0,
            "low_price": 0,
            "max_profit_pct": 1.24,
            "max_loss_pct": -4.07
          },
          {
            "code": "027360",
            "name": "아주IB투자",
            "entry_price": 18530,
            "exit_price": 17974,
            "quantity": 108,
            "return_pct": -3.0,
            "return_amount": -60048,
            "exit_type": "loss",
            "entry_time": "09:05",
            "exit_time": "09:38",
            "high_price": 0,
            "low_price": 0,
            "max_profit_pct": 2.37,
            "max_loss_pct": -4.8
          },
          {
            "code": "036540",
            "name": "SFA반도체",
            "entry_price": 10270,
            "exit_price": 9961,
            "quantity": 195,
            "return_pct": -3.01,
            "return_amount": -60255,
            "exit_type": "loss",
            "entry_time": "09:05",
            "exit_time": "09:31",
            "high_price": 0,
            "low_price": 0,
            "max_profit_pct": 1.56,
            "max_loss_pct": -5.26
          },
          {
            "code": "123690",
            "name": "한국화장품",
            "entry_price": 8850,
            "exit_price": 8940,
            "quantity": 226,
            "return_pct": 1.02,
            "return_amount": 20340,
            "exit_type": "close",
            "entry_time": "09:05",
            "exit_time": "15:20",
            "high_price": 0,
            "low_price": 0,
            "max_profit_pct": 2.26,
            "max_loss_pct": 0
          }
        ]
      }
    }
  },
  "leaderboard": {
    "ranking": [
      {
        "team_id": "team_a",
        "team_name": "Alpha Momentum",
        "emoji": "🔴",
        "elo": 1262,
        "rank": 4,
        "total_1st": 8,
        "total_2nd": 4,
        "total_3rd": 1,
        "total_4th": 1,
        "best_day_return": 22.52,
        "worst_day_return": 0,
        "elo_rank": 1
      },
      {
        "team_id": "team_e",
        "team_name": "Echo Frontier",
        "emoji": "🟣",
        "elo": 1198,
        "rank": 1,
        "total_1st": 2,
        "total_2nd": 2,
        "total_3rd": 3,
        "total_4th": 3,
        "best_day_return": 20.73,
        "worst_day_return": 0,
        "total_5th": 2,
        "elo_rank": 2
      },
      {
        "team_id": "team_i",
        "team_name": "Alpha-Delta Hybrid",
        "emoji": "🔀",
        "elo": 1083,
        "rank": 3,
        "total_1st": 0,
        "total_2nd": 0,
        "total_3rd": 2,
        "total_4th": 1,
        "best_day_return": 7.57,
        "worst_day_return": -4.21,
        "reset_at": "2026-04-23",
        "reset_reason": "Hybrid 로직 수정 전까지 team_a 결과 복제(ISSUE-010). 공정 비교 위해 통계 초기화",
        "elo_rank": 3
      },
      {
        "team_id": "team_h",
        "team_name": "Theta Sector",
        "emoji": "🔷",
        "elo": 1012,
        "rank": 2,
        "total_1st": 0,
        "total_2nd": 1,
        "total_3rd": 0,
        "total_4th": 1,
        "best_day_return": 8.11,
        "worst_day_return": -6.61,
        "total_7th": 2,
        "total_6th": 1,
        "total_5th": 1,
        "elo_rank": 4
      },
      {
        "team_id": "team_d",
        "team_name": "Delta Theme",
        "emoji": "🟡",
        "elo": 933,
        "rank": 6,
        "total_1st": 3,
        "total_2nd": 4,
        "total_3rd": 2,
        "total_4th": 1,
        "best_day_return": 20.1,
        "worst_day_return": -12.82,
        "total_5th": 1,
        "total_8th": 2,
        "total_6th": 1,
        "elo_rank": 5
      },
      {
        "team_id": "team_c",
        "team_name": "Gamma Disclosure",
        "emoji": "🟢",
        "elo": 929,
        "rank": 5,
        "total_1st": 1,
        "total_2nd": 2,
        "total_3rd": 3,
        "total_4th": 2,
        "best_day_return": 10.03,
        "worst_day_return": -9.01,
        "total_5th": 3,
        "total_8th": 1,
        "total_7th": 1,
        "total_6th": 1,
        "elo_rank": 6
      },
      {
        "team_id": "team_g",
        "team_name": "Kappa Turtle",
        "emoji": "🐢",
        "elo": 873,
        "rank": 8,
        "total_1st": 0,
        "total_2nd": 0,
        "total_3rd": 1,
        "total_4th": 0,
        "best_day_return": 8.98,
        "worst_day_return": -7.47,
        "total_8th": 3,
        "total_7th": 1,
        "total_5th": 1,
        "elo_rank": 7
      },
      {
        "team_id": "team_f",
        "team_name": "Zeta Volatility",
        "emoji": "🟠",
        "elo": 837,
        "rank": 7,
        "total_1st": 0,
        "total_2nd": 0,
        "total_3rd": 1,
        "total_4th": 1,
        "best_day_return": 2.16,
        "worst_day_return": -7.02,
        "total_5th": 2,
        "total_6th": 3,
        "total_7th": 2,
        "elo_rank": 8
      }
    ],
    "recent_history": [
      {
        "date": "20260421",
        "ranking": [
          {
            "rank": 1,
            "team_id": "team_d",
            "total_return": 20.1,
            "win_rate": 100.0,
            "trades": 5
          },
          {
            "rank": 2,
            "team_id": "team_a",
            "total_return": 13.12,
            "win_rate": 80.0,
            "trades": 5
          },
          {
            "rank": 3,
            "team_id": "team_e",
            "total_return": 0,
            "win_rate": 0,
            "trades": 0
          },
          {
            "rank": 4,
            "team_id": "team_f",
            "total_return": 0,
            "win_rate": 0,
            "trades": 0
          },
          {
            "rank": 5,
            "team_id": "team_h",
            "total_return": 0,
            "win_rate": 0,
            "trades": 0
          },
          {
            "rank": 6,
            "team_id": "team_g",
            "total_return": 0,
            "win_rate": 0,
            "trades": 0
          },
          {
            "rank": 7,
            "team_id": "team_c",
            "total_return": -1.05,
            "win_rate": 50.0,
            "trades": 2
          }
        ]
      },
      {
        "date": "20260422",
        "ranking": [
          {
            "rank": 1,
            "team_id": "team_c",
            "total_return": 10.03,
            "win_rate": 60.0,
            "trades": 5
          },
          {
            "rank": 2,
            "team_id": "team_d",
            "total_return": 9.85,
            "win_rate": 60.0,
            "trades": 5
          },
          {
            "rank": 3,
            "team_id": "team_a",
            "total_return": 7.19,
            "win_rate": 60.0,
            "trades": 5
          },
          {
            "rank": 4,
            "team_id": "team_e",
            "total_return": 0,
            "win_rate": 0,
            "trades": 0
          },
          {
            "rank": 5,
            "team_id": "team_f",
            "total_return": 0,
            "win_rate": 0,
            "trades": 0
          },
          {
            "rank": 6,
            "team_id": "team_h",
            "total_return": 0,
            "win_rate": 0,
            "trades": 0
          },
          {
            "rank": 7,
            "team_id": "team_g",
            "total_return": 0,
            "win_rate": 0,
            "trades": 0
          }
        ]
      },
      {
        "date": "20260423",
        "ranking": [
          {
            "rank": 1,
            "team_id": "team_a",
            "total_return": 11.78,
            "win_rate": 60.0,
            "trades": 5
          },
          {
            "rank": 2,
            "team_id": "team_e",
            "total_return": 0.99,
            "win_rate": 40.0,
            "trades": 5
          },
          {
            "rank": 3,
            "team_id": "team_i",
            "total_return": -4.21,
            "win_rate": 20.0,
            "trades": 5
          },
          {
            "rank": 4,
            "team_id": "team_h",
            "total_return": -6.61,
            "win_rate": 40.0,
            "trades": 5
          },
          {
            "rank": 5,
            "team_id": "team_g",
            "total_return": -7.0,
            "win_rate": 20.0,
            "trades": 5
          },
          {
            "rank": 6,
            "team_id": "team_f",
            "total_return": -7.02,
            "win_rate": 20.0,
            "trades": 5
          },
          {
            "rank": 7,
            "team_id": "team_c",
            "total_return": -9.01,
            "win_rate": 0.0,
            "trades": 3
          },
          {
            "rank": 8,
            "team_id": "team_d",
            "total_return": -12.82,
            "win_rate": 0.0,
            "trades": 5
          }
        ]
      },
      {
        "date": "20260424",
        "ranking": [
          {
            "rank": 1,
            "team_id": "team_e",
            "total_return": 20.73,
            "win_rate": 100.0,
            "trades": 5
          },
          {
            "rank": 2,
            "team_id": "team_a",
            "total_return": 11.38,
            "win_rate": 80.0,
            "trades": 5
          },
          {
            "rank": 3,
            "team_id": "team_g",
            "total_return": 8.98,
            "win_rate": 60.0,
            "trades": 5
          },
          {
            "rank": 4,
            "team_id": "team_i",
            "total_return": 7.57,
            "win_rate": 60.0,
            "trades": 5
          },
          {
            "rank": 5,
            "team_id": "team_h",
            "total_return": 6.7,
            "win_rate": 60.0,
            "trades": 5
          },
          {
            "rank": 6,
            "team_id": "team_c",
            "total_return": 5.0,
            "win_rate": 100.0,
            "trades": 1
          },
          {
            "rank": 7,
            "team_id": "team_f",
            "total_return": 2.16,
            "win_rate": 40.0,
            "trades": 5
          },
          {
            "rank": 8,
            "team_id": "team_d",
            "total_return": -1.8,
            "win_rate": 20.0,
            "trades": 5
          }
        ]
      },
      {
        "date": "20260427",
        "ranking": [
          {
            "rank": 1,
            "team_id": "team_e",
            "total_return": 19.43,
            "win_rate": 100.0,
            "trades": 5
          },
          {
            "rank": 2,
            "team_id": "team_h",
            "total_return": 8.11,
            "win_rate": 80.0,
            "trades": 5
          },
          {
            "rank": 3,
            "team_id": "team_i",
            "total_return": 4.12,
            "win_rate": 60.0,
            "trades": 5
          },
          {
            "rank": 4,
            "team_id": "team_a",
            "total_return": 3.05,
            "win_rate": 60.0,
            "trades": 5
          },
          {
            "rank": 5,
            "team_id": "team_c",
            "total_return": 2.0,
            "win_rate": 50.0,
            "trades": 2
          },
          {
            "rank": 6,
            "team_id": "team_d",
            "total_return": 0.82,
            "win_rate": 40.0,
            "trades": 5
          },
          {
            "rank": 7,
            "team_id": "team_f",
            "total_return": -2.99,
            "win_rate": 40.0,
            "trades": 5
          },
          {
            "rank": 8,
            "team_id": "team_g",
            "total_return": -7.47,
            "win_rate": 40.0,
            "trades": 5
          }
        ]
      }
    ],
    "total_days": 14,
    "last_updated": "2026-04-27 18:43:57"
  }
}