{
  "date": "20260507",
  "n_trades": 30,
  "n_real_ohlc_missing": 0,
  "n_dir_mismatch": 8,
  "n_amt_mismatch": 0,
  "n_ok": 22,
  "mismatch_rate_pct": 26.7,
  "team_pnl": {
    "team_a": {
      "sim_amount": -389448,
      "real_amount": -488175,
      "diff_amount": -98727,
      "sim_pct": -3.89,
      "real_pct": -4.88,
      "diff_pct": -0.99
    },
    "team_d": {
      "sim_amount": 128598,
      "real_amount": -70108,
      "diff_amount": -198706,
      "sim_pct": 1.29,
      "real_pct": -0.7,
      "diff_pct": -1.99
    },
    "team_e": {
      "sim_amount": -371549,
      "real_amount": -351835,
      "diff_amount": 19714,
      "sim_pct": -3.72,
      "real_pct": -3.52,
      "diff_pct": 0.2
    },
    "team_f": {
      "sim_amount": -222152,
      "real_amount": -165101,
      "diff_amount": 57051,
      "sim_pct": -2.22,
      "real_pct": -1.65,
      "diff_pct": 0.57
    },
    "team_h": {
      "sim_amount": -371887,
      "real_amount": -354804,
      "diff_amount": 17083,
      "sim_pct": -3.72,
      "real_pct": -3.55,
      "diff_pct": 0.17
    },
    "team_i": {
      "sim_amount": 61703,
      "real_amount": -153357,
      "diff_amount": -215060,
      "sim_pct": 0.62,
      "real_pct": -1.53,
      "diff_pct": -2.15
    }
  },
  "rows": [
    {
      "team": "team_a",
      "code": "018880",
      "name": "한온시스템",
      "sim_entry": 5490,
      "real_open": 5450,
      "sim_exit": 5315,
      "real_close": 4900,
      "real_high": 5560,
      "real_low": 4860,
      "sim_ret_pct": -3.19,
      "real_ret_pct": -3.0,
      "diff_pct": 0.19,
      "sim_exit_type": "loss",
      "real_exit_type": "loss",
      "flag": "OK",
      "sim_amount": -102900,
      "real_amount": -96432
    },
    {
      "team": "team_a",
      "code": "003530",
      "name": "한화투자증권",
      "sim_entry": 9018,
      "real_open": 9260,
      "sim_exit": 8730,
      "real_close": 8490,
      "real_high": 9260,
      "real_low": 8350,
      "sim_ret_pct": -3.19,
      "real_ret_pct": -3.0,
      "diff_pct": 0.19,
      "sim_exit_type": "loss",
      "real_exit_type": "loss",
      "flag": "OK",
      "sim_amount": -103104,
      "real_amount": -99524
    },
    {
      "team": "team_a",
      "code": "016360",
      "name": "삼성증권",
      "sim_entry": 144187,
      "real_open": 147100,
      "sim_exit": 145200,
      "real_close": 145200,
      "real_high": 147700,
      "real_low": 141000,
      "sim_ret_pct": 0.7,
      "real_ret_pct": -3.0,
      "diff_pct": -3.7,
      "sim_exit_type": "close",
      "real_exit_type": "loss",
      "flag": "DIR",
      "sim_amount": 22286,
      "real_amount": -97086
    },
    {
      "team": "team_a",
      "code": "212710",
      "name": "아이에스티이",
      "sim_entry": 10871,
      "real_open": 11050,
      "sim_exit": 10524,
      "real_close": 10420,
      "real_high": 11050,
      "real_low": 10020,
      "sim_ret_pct": -3.19,
      "real_ret_pct": -3.0,
      "diff_pct": 0.19,
      "sim_exit_type": "loss",
      "real_exit_type": "loss",
      "flag": "OK",
      "sim_amount": -103059,
      "real_amount": -98604
    },
    {
      "team": "team_a",
      "code": "382900",
      "name": "범한퓨얼셀",
      "sim_entry": 38727,
      "real_open": 38750,
      "sim_exit": 37490,
      "real_close": 36050,
      "real_high": 38900,
      "real_low": 35450,
      "sim_ret_pct": -3.19,
      "real_ret_pct": -3.0,
      "diff_pct": 0.19,
      "sim_exit_type": "loss",
      "real_exit_type": "loss",
      "flag": "OK",
      "sim_amount": -102671,
      "real_amount": -96529
    },
    {
      "team": "team_d",
      "code": "222800",
      "name": "심텍",
      "sim_entry": 103105,
      "real_open": 102400,
      "sim_exit": 108940,
      "real_close": 106500,
      "real_high": 111200,
      "real_low": 99500,
      "sim_ret_pct": 5.66,
      "real_ret_pct": 5.0,
      "diff_pct": -0.66,
      "sim_exit_type": "trailing",
      "real_exit_type": "profit",
      "flag": "DIR",
      "sim_amount": 128370,
      "real_amount": 112640
    },
    {
      "team": "team_d",
      "code": "003670",
      "name": "포스코퓨처엠",
      "sim_entry": 282564,
      "real_open": 288000,
      "sim_exit": 291858,
      "real_close": 296000,
      "real_high": 298500,
      "real_low": 274500,
      "sim_ret_pct": 3.29,
      "real_ret_pct": -3.0,
      "diff_pct": -6.29,
      "sim_exit_type": "trailing",
      "real_exit_type": "loss",
      "flag": "DIR",
      "sim_amount": 74352,
      "real_amount": -69120
    },
    {
      "team": "team_d",
      "code": "066570",
      "name": "LG전자",
      "sim_entry": 155209,
      "real_open": 155000,
      "sim_exit": 150253,
      "real_close": 148700,
      "real_high": 155700,
      "real_low": 145000,
      "sim_ret_pct": -3.19,
      "real_ret_pct": -3.0,
      "diff_pct": 0.19,
      "sim_exit_type": "loss",
      "real_exit_type": "loss",
      "flag": "OK",
      "sim_amount": -74340,
      "real_amount": -69750
    },
    {
      "team": "team_d",
      "code": "098460",
      "name": "고영",
      "sim_entry": 40881,
      "real_open": 41800,
      "sim_exit": 40150,
      "real_close": 40150,
      "real_high": 41900,
      "real_low": 39600,
      "sim_ret_pct": -1.79,
      "real_ret_pct": -3.0,
      "diff_pct": -1.21,
      "sim_exit_type": "close",
      "real_exit_type": "loss",
      "flag": "DIR",
      "sim_amount": -41667,
      "real_amount": -71478
    },
    {
      "team": "team_d",
      "code": "375500",
      "name": "DL이앤씨",
      "sim_entry": 98396,
      "real_open": 99100,
      "sim_exit": 100217,
      "real_close": 100300,
      "real_high": 101300,
      "real_low": 96200,
      "sim_ret_pct": 1.85,
      "real_ret_pct": 1.21,
      "diff_pct": -0.64,
      "sim_exit_type": "trailing",
      "real_exit_type": "close",
      "flag": "OK",
      "sim_amount": 41883,
      "real_amount": 27600
    },
    {
      "team": "team_e",
      "code": "089790",
      "name": "제이티",
      "sim_entry": 6883,
      "real_open": 6840,
      "sim_exit": 6663,
      "real_close": 6700,
      "real_high": 7110,
      "real_low": 6390,
      "sim_ret_pct": -3.2,
      "real_ret_pct": -3.0,
      "diff_pct": 0.2,
      "sim_exit_type": "loss",
      "real_exit_type": "loss",
      "flag": "OK",
      "sim_amount": -74360,
      "real_amount": -69628
    },
    {
      "team": "team_e",
      "code": "419080",
      "name": "엔젯",
      "sim_entry": 6392,
      "real_open": 6430,
      "sim_exit": 6188,
      "real_close": 5700,
      "real_high": 6430,
      "real_low": 5650,
      "sim_ret_pct": -3.19,
      "real_ret_pct": -3.0,
      "diff_pct": 0.19,
      "sim_exit_type": "loss",
      "real_exit_type": "loss",
      "flag": "OK",
      "sim_amount": -74256,
      "real_amount": -70252
    },
    {
      "team": "team_e",
      "code": "204270",
      "name": "제이앤티씨",
      "sim_entry": 23196,
      "real_open": 23600,
      "sim_exit": 22455,
      "real_close": 20800,
      "real_high": 23650,
      "real_low": 20400,
      "sim_ret_pct": -3.19,
      "real_ret_pct": -3.0,
      "diff_pct": 0.19,
      "sim_exit_type": "loss",
      "real_exit_type": "loss",
      "flag": "OK",
      "sim_amount": -74100,
      "real_amount": -70800
    },
    {
      "team": "team_e",
      "code": "037030",
      "name": "파워넷",
      "sim_entry": 10070,
      "real_open": 10070,
      "sim_exit": 9748,
      "real_close": 8210,
      "real_high": 10400,
      "real_low": 7960,
      "sim_ret_pct": -3.2,
      "real_ret_pct": -3.0,
      "diff_pct": 0.2,
      "sim_exit_type": "loss",
      "real_exit_type": "loss",
      "flag": "OK",
      "sim_amount": -74382,
      "real_amount": -69993
    },
    {
      "team": "team_e",
      "code": "452450",
      "name": "피아이이",
      "sim_entry": 7795,
      "real_open": 7920,
      "sim_exit": 7546,
      "real_close": 7170,
      "real_high": 7930,
      "real_low": 7150,
      "sim_ret_pct": -3.19,
      "real_ret_pct": -3.0,
      "diff_pct": 0.19,
      "sim_exit_type": "loss",
      "real_exit_type": "loss",
      "flag": "OK",
      "sim_amount": -74451,
      "real_amount": -71162
    },
    {
      "team": "team_f",
      "code": "155650",
      "name": "와이엠씨",
      "sim_entry": 4393,
      "real_open": 4350,
      "sim_exit": 4253,
      "real_close": 4135,
      "real_high": 4460,
      "real_low": 4100,
      "sim_ret_pct": -3.19,
      "real_ret_pct": -3.0,
      "diff_pct": 0.19,
      "sim_exit_type": "loss",
      "real_exit_type": "loss",
      "flag": "OK",
      "sim_amount": -74060,
      "real_amount": -69299
    },
    {
      "team": "team_f",
      "code": "450330",
      "name": "하스",
      "sim_entry": 7454,
      "real_open": 7500,
      "sim_exit": 7216,
      "real_close": 7120,
      "real_high": 7540,
      "real_low": 7020,
      "sim_ret_pct": -3.19,
      "real_ret_pct": -3.0,
      "diff_pct": 0.19,
      "sim_exit_type": "loss",
      "real_exit_type": "loss",
      "flag": "OK",
      "sim_amount": -74256,
      "real_amount": -70200
    },
    {
      "team": "team_f",
      "code": "006660",
      "name": "삼성공조",
      "sim_entry": 14448,
      "real_open": 14660,
      "sim_exit": 13987,
      "real_close": 13630,
      "real_high": 14660,
      "real_low": 13630,
      "sim_ret_pct": -3.19,
      "real_ret_pct": -3.0,
      "diff_pct": 0.19,
      "sim_exit_type": "loss",
      "real_exit_type": "loss",
      "flag": "OK",
      "sim_amount": -74221,
      "real_amount": -70840
    },
    {
      "team": "team_f",
      "code": "014280",
      "name": "금강공업",
      "sim_entry": 5901,
      "real_open": 5790,
      "sim_exit": 6090,
      "real_close": 5810,
      "real_high": 6180,
      "real_low": 5650,
      "sim_ret_pct": 3.2,
      "real_ret_pct": 5.0,
      "diff_pct": 1.8,
      "sim_exit_type": "trailing",
      "real_exit_type": "profit",
      "flag": "DIR",
      "sim_amount": 74466,
      "real_amount": 113866
    },
    {
      "team": "team_f",
      "code": "356680",
      "name": "엑스게이트",
      "sim_entry": 17444,
      "real_open": 17200,
      "sim_exit": 16887,
      "real_close": 16670,
      "real_high": 17930,
      "real_low": 16500,
      "sim_ret_pct": -3.19,
      "real_ret_pct": -3.0,
      "diff_pct": 0.19,
      "sim_exit_type": "loss",
      "real_exit_type": "loss",
      "flag": "OK",
      "sim_amount": -74081,
      "real_amount": -68628
    },
    {
      "team": "team_h",
      "code": "005930",
      "name": "삼성전자",
      "sim_entry": 276051,
      "real_open": 272000,
      "sim_exit": 267235,
      "real_close": 271500,
      "real_high": 277000,
      "real_low": 260000,
      "sim_ret_pct": -3.19,
      "real_ret_pct": -3.0,
      "diff_pct": 0.19,
      "sim_exit_type": "loss",
      "real_exit_type": "loss",
      "flag": "OK",
      "sim_amount": -70528,
      "real_amount": -65280
    },
    {
      "team": "team_h",
      "code": "011790",
      "name": "SKC",
      "sim_entry": 181963,
      "real_open": 184000,
      "sim_exit": 176152,
      "real_close": 174100,
      "real_high": 184400,
      "real_low": 165000,
      "sim_ret_pct": -3.19,
      "real_ret_pct": -3.0,
      "diff_pct": 0.19,
      "sim_exit_type": "loss",
      "real_exit_type": "loss",
      "flag": "OK",
      "sim_amount": -75543,
      "real_amount": -71760
    },
    {
      "team": "team_h",
      "code": "006800",
      "name": "미래에셋증권",
      "sim_entry": 81162,
      "real_open": 82800,
      "sim_exit": 78570,
      "real_close": 79000,
      "real_high": 82800,
      "real_low": 75700,
      "sim_ret_pct": -3.19,
      "real_ret_pct": -3.0,
      "diff_pct": 0.19,
      "sim_exit_type": "loss",
      "real_exit_type": "loss",
      "flag": "OK",
      "sim_amount": -75168,
      "real_amount": -72036
    },
    {
      "team": "team_h",
      "code": "028260",
      "name": "삼성물산",
      "sim_entry": 394287,
      "real_open": 392000,
      "sim_exit": 381695,
      "real_close": 405000,
      "real_high": 405500,
      "real_low": 367000,
      "sim_ret_pct": -3.19,
      "real_ret_pct": -3.0,
      "diff_pct": 0.19,
      "sim_exit_type": "loss",
      "real_exit_type": "loss",
      "flag": "OK",
      "sim_amount": -75552,
      "real_amount": -70560
    },
    {
      "team": "team_h",
      "code": "001440",
      "name": "대한전선",
      "sim_entry": 65330,
      "real_open": 69600,
      "sim_exit": 63244,
      "real_close": 64100,
      "real_high": 69600,
      "real_low": 60900,
      "sim_ret_pct": -3.19,
      "real_ret_pct": -3.0,
      "diff_pct": 0.19,
      "sim_exit_type": "loss",
      "real_exit_type": "loss",
      "flag": "OK",
      "sim_amount": -75096,
      "real_amount": -75168
    },
    {
      "team": "team_i",
      "code": "018880",
      "name": "한온시스템",
      "sim_entry": 5490,
      "real_open": 5450,
      "sim_exit": 5315,
      "real_close": 4900,
      "real_high": 5560,
      "real_low": 4860,
      "sim_ret_pct": -3.19,
      "real_ret_pct": -3.0,
      "diff_pct": 0.19,
      "sim_exit_type": "loss",
      "real_exit_type": "loss",
      "flag": "OK",
      "sim_amount": -70525,
      "real_amount": -66092
    },
    {
      "team": "team_i",
      "code": "003530",
      "name": "한화투자증권",
      "sim_entry": 9018,
      "real_open": 9260,
      "sim_exit": 8730,
      "real_close": 8490,
      "real_high": 9260,
      "real_low": 8350,
      "sim_ret_pct": -3.19,
      "real_ret_pct": -3.0,
      "diff_pct": 0.19,
      "sim_exit_type": "loss",
      "real_exit_type": "loss",
      "flag": "OK",
      "sim_amount": -70560,
      "real_amount": -68110
    },
    {
      "team": "team_i",
      "code": "016360",
      "name": "삼성증권",
      "sim_entry": 144187,
      "real_open": 147100,
      "sim_exit": 145200,
      "real_close": 145200,
      "real_high": 147700,
      "real_low": 141000,
      "sim_ret_pct": 0.7,
      "real_ret_pct": -3.0,
      "diff_pct": -3.7,
      "sim_exit_type": "close",
      "real_exit_type": "loss",
      "flag": "DIR",
      "sim_amount": 15195,
      "real_amount": -66195
    },
    {
      "team": "team_i",
      "code": "222800",
      "name": "심텍",
      "sim_entry": 103105,
      "real_open": 102400,
      "sim_exit": 108940,
      "real_close": 106500,
      "real_high": 111200,
      "real_low": 99500,
      "sim_ret_pct": 5.66,
      "real_ret_pct": 5.0,
      "diff_pct": -0.66,
      "sim_exit_type": "trailing",
      "real_exit_type": "profit",
      "flag": "DIR",
      "sim_amount": 122535,
      "real_amount": 107520
    },
    {
      "team": "team_i",
      "code": "003670",
      "name": "포스코퓨처엠",
      "sim_entry": 282564,
      "real_open": 288000,
      "sim_exit": 291858,
      "real_close": 296000,
      "real_high": 298500,
      "real_low": 274500,
      "sim_ret_pct": 3.29,
      "real_ret_pct": -3.0,
      "diff_pct": -6.29,
      "sim_exit_type": "trailing",
      "real_exit_type": "loss",
      "flag": "DIR",
      "sim_amount": 65058,
      "real_amount": -60480
    }
  ]
}