{"code": "00680K", "name": "미래에셋증권2우B", "ohlcv": [{"date": "2026-04-24", "open": 20500, "high": 20550, "low": 19990, "close": 20000, "volume": 398192}, {"date": "2026-04-27", "open": 20100, "high": 20700, "low": 19600, "close": 20300, "volume": 448953}, {"date": "2026-04-28", "open": 20350, "high": 20800, "low": 20050, "close": 20400, "volume": 382173}, {"date": "2026-04-29", "open": 20400, "high": 20450, "low": 19910, "close": 20300, "volume": 453132}, {"date": "2026-04-30", "open": 20300, "high": 20500, "low": 19230, "close": 19510, "volume": 937742}, {"date": "2026-05-04", "open": 19860, "high": 20950, "low": 19690, "close": 20550, "volume": 988154}, {"date": "2026-05-06", "open": 21500, "high": 24250, "low": 20950, "close": 23800, "volume": 2539884}, {"date": "2026-05-07", "open": 23800, "high": 23850, "low": 22100, "close": 22700, "volume": 979175}, {"date": "2026-05-08", "open": 22400, "high": 23150, "low": 22050, "close": 22900, "volume": 536506}, {"date": "2026-05-11", "open": 23500, "high": 24100, "low": 22750, "close": 22950, "volume": 628896}, {"date": "2026-05-12", "open": 23650, "high": 23700, "low": 20300, "close": 21000, "volume": 892844}, {"date": "2026-05-13", "open": 20750, "high": 20800, "low": 20050, "close": 20150, "volume": 690616}, {"date": "2026-05-14", "open": 20200, "high": 20500, "low": 19700, "close": 19810, "volume": 440870}, {"date": "2026-05-15", "open": 20200, "high": 20700, "low": 18640, "close": 18900, "volume": 1038715}, {"date": "2026-05-18", "open": 19160, "high": 19300, "low": 17900, "close": 18940, "volume": 711824}, {"date": "2026-05-19", "open": 18940, "high": 19100, "low": 17700, "close": 18110, "volume": 497184}, {"date": "2026-05-20", "open": 18090, "high": 18090, "low": 16460, "close": 16770, "volume": 1105481}, {"date": "2026-05-21", "open": 17400, "high": 17820, "low": 17000, "close": 17770, "volume": 869429}, {"date": "2026-05-22", "open": 17990, "high": 18440, "low": 17790, "close": 17910, "volume": 381971}, {"date": "2026-05-26", "open": 18300, "high": 18590, "low": 17400, "close": 17450, "volume": 474559}, {"date": "2026-05-27", "open": 17650, "high": 17820, "low": 16810, "close": 16980, "volume": 484490}, {"date": "2026-05-28", "open": 16980, "high": 16980, "low": 15640, "close": 16270, "volume": 621983}, {"date": "2026-05-29", "open": 16350, "high": 16370, "low": 15310, "close": 15610, "volume": 1678261}]}