{
  "updated_at": "2026-07-08 18:08:02",
  "positions": [
    {
      "code": "010060",
      "name": "OCI홀딩스",
      "state": "FULL",
      "avg_price": 203000,
      "current_price": 197900,
      "total_quantity": 2,
      "entry_date": "2026-07-07",
      "entry_price": 203000,
      "unrealized_pnl": -10200,
      "unrealized_pnl_pct": -2.512315270935961,
      "selection_reason": "고점 40.8%",
      "sector": "기타",
      "market_cap": 3976759416000,
      "trading_value": 33318611200,
      "high_20d": 335500,
      "entries": [
        {
          "price": 203000,
          "quantity": 2,
          "date": "2026-07-07",
          "time": "13:30:28"
        }
      ],
      "exits": []
    },
    {
      "code": "440110",
      "name": "파두",
      "state": "FULL",
      "avg_price": 70500,
      "current_price": 70000,
      "total_quantity": 8,
      "entry_date": "2026-07-07",
      "entry_price": 70500,
      "unrealized_pnl": -4000,
      "unrealized_pnl_pct": -0.7092198581560294,
      "selection_reason": "5일 15.3% | 10일 37.4% | 고점 38.9%",
      "sector": "기타",
      "market_cap": 3988073589200,
      "trading_value": 51664719800,
      "high_20d": 118800,
      "entries": [
        {
          "price": 70500,
          "quantity": 8,
          "date": "2026-07-07",
          "time": "13:30:28"
        }
      ],
      "exits": []
    },
    {
      "code": "095340",
      "name": "ISC",
      "state": "FULL",
      "avg_price": 151300,
      "current_price": 150100,
      "total_quantity": 3,
      "entry_date": "2026-07-07",
      "entry_price": 151300,
      "unrealized_pnl": -3600,
      "unrealized_pnl_pct": -0.7931262392597449,
      "selection_reason": "5일 17.9% | 10일 23.0% | 고점 38.3%",
      "sector": "기타",
      "market_cap": 3539908686000,
      "trading_value": 49129285750,
      "high_20d": 247500,
      "entries": [
        {
          "price": 151300,
          "quantity": 3,
          "date": "2026-07-07",
          "time": "13:30:28"
        }
      ],
      "exits": []
    },
    {
      "code": "307950",
      "name": "현대오토에버",
      "state": "FULL",
      "avg_price": 480500,
      "current_price": 480500,
      "total_quantity": 1,
      "entry_date": "2026-07-07",
      "entry_price": 480500,
      "unrealized_pnl": 0,
      "unrealized_pnl_pct": 0.0,
      "selection_reason": "10일 20.8% | 고점 36.6%",
      "sector": "기타",
      "market_cap": 13849110910000,
      "trading_value": 50064077000,
      "high_20d": 780000,
      "entries": [
        {
          "price": 480500,
          "quantity": 1,
          "date": "2026-07-07",
          "time": "19:07:02"
        }
      ],
      "exits": []
    },
    {
      "code": "083650",
      "name": "비에이치아이",
      "state": "FULL",
      "avg_price": 51400,
      "current_price": 51400,
      "total_quantity": 11,
      "entry_date": "2026-07-07",
      "entry_price": 51400,
      "unrealized_pnl": 0,
      "unrealized_pnl_pct": 0.0,
      "selection_reason": "고점 35.7%",
      "sector": "기타",
      "market_cap": 1667901812500,
      "trading_value": 10512187150,
      "high_20d": 80600,
      "entries": [
        {
          "price": 51400,
          "quantity": 11,
          "date": "2026-07-07",
          "time": "19:07:02"
        }
      ],
      "exits": []
    }
  ],
  "cooldown_until": {
    "403870": "2026-07-08",
    "066570": "2026-07-08",
    "454910": "2026-07-09",
    "010170": "2026-07-09",
    "000250": "2026-07-09",
    "043260": "2026-07-09",
    "031330": "2026-07-09",
    "001740": "2026-07-09",
    "247540": "2026-07-10",
    "020150": "2026-07-10",
    "131970": "2026-07-10",
    "007810": "2026-07-13",
    "001820": "2026-07-13",
    "085620": "2026-07-14",
    "347700": "2026-07-14",
    "319400": "2026-07-14",
    "183300": "2026-07-14",
    "093370": "2026-07-14",
    "108490": "2026-07-14",
    "047040": "2026-07-14"
  },
  "stats": {
    "total_capital": 3000000,
    "current_capital": 1282707,
    "used_capital": 2469800,
    "open_positions": 5,
    "total_trades": 182,
    "win_rate": 21.4,
    "total_return": -57.24,
    "total_return_simple": -318.3,
    "realized_pnl": -1699493,
    "unrealized_pnl": -17800,
    "avg_return": -1.75
  }
}