{
  "strategy_id": "theme_policy",
  "strategy_name": "테마/정책",
  "date": "20260708",
  "selected_at": "2026-07-09 20:05:41",
  "count": 5,
  "candidates": [
    {
      "code": "352820",
      "name": "하이브",
      "price": 230000,
      "change_pct": -0.86,
      "score": 78.4,
      "score_detail": {
        "theme_relevance": 40.0,
        "change_pct": 3.4,
        "trading_value": 20.0,
        "theme_strength": 15.0,
        "themes": [
          "부동산",
          "비금속",
          "종이·목재",
          "통신",
          "운송·창고",
          "음식료·담배",
          "통신",
          "오락·문화",
          "음식료·담배",
          "기타제조"
        ]
      },
      "rank": 1,
      "market_cap": 9913517270000,
      "volume": 380347,
      "trading_value": 86827983000,
      "themes": [
        {
          "code": "98",
          "name": "음원/음반"
        },
        {
          "code": "128",
          "name": "엔터테인먼트"
        }
      ]
    },
    {
      "code": "035720",
      "name": "카카오",
      "price": 34650,
      "change_pct": -2.12,
      "score": 75.4,
      "score_detail": {
        "theme_relevance": 40.0,
        "change_pct": 3.0,
        "trading_value": 17.4,
        "theme_strength": 15.0,
        "themes": [
          "부동산",
          "비금속",
          "종이·목재",
          "통신",
          "운송·창고",
          "음식료·담배",
          "통신",
          "오락·문화",
          "음식료·담배",
          "기타제조"
        ]
      },
      "rank": 2,
      "market_cap": 15349294075500,
      "volume": 2205415,
      "trading_value": 75736950725,
      "themes": [
        {
          "code": "317",
          "name": "SNS(소셜네트워크서비스)"
        },
        {
          "code": "480",
          "name": "메타버스(Metaverse)"
        },
        {
          "code": "331",
          "name": "가상화폐(비트코인 등)"
        },
        {
          "code": "98",
          "name": "음원/음반"
        },
        {
          "code": "489",
          "name": "카카오뱅크(kakao BANK)"
        },
        {
          "code": "128",
          "name": "엔터테인먼트"
        },
        {
          "code": "343",
          "name": "인터넷은행"
        },
        {
          "code": "529",
          "name": "AI 챗봇(챗GPT 등)"
        },
        {
          "code": "302",
          "name": "음성인식"
        },
        {
          "code": "270",
          "name": "모바일콘텐츠(스마트폰/태블릿PC)"
        },
        {
          "code": "387",
          "name": "블록체인"
        },
        {
          "code": "342",
          "name": "핀테크(FinTech)"
        },
        {
          "code": "462",
          "name": "UAM(도심항공모빌리티)"
        },
        {
          "code": "488",
          "name": "웹툰"
        }
      ]
    },
    {
      "code": "316140",
      "name": "우리금융지주",
      "price": 30700,
      "change_pct": -2.69,
      "score": 62.9,
      "score_detail": {
        "theme_relevance": 24.0,
        "change_pct": 2.7,
        "trading_value": 16.8,
        "theme_strength": 19.4,
        "themes": [
          "통신",
          "음식료·담배",
          "통신",
          "오락·문화",
          "음식료·담배",
          "기타제조"
        ]
      },
      "rank": 3,
      "market_cap": 22352353237400,
      "volume": 2351509,
      "trading_value": 72737145125,
      "themes": [
        {
          "code": "165",
          "name": "은행"
        },
        {
          "code": "111",
          "name": "지주사"
        },
        {
          "code": "567",
          "name": "밸류업(24년 기업가치 제고계획 발표)"
        },
        {
          "code": "571",
          "name": "밸류업(25년 기업가치 제고계획 발표)"
        },
        {
          "code": "568",
          "name": "코리아 밸류업 지수(Korea Value-up Index)"
        }
      ]
    },
    {
      "code": "005387",
      "name": "현대차2우B",
      "price": 211000,
      "change_pct": -0.94,
      "score": 51.1,
      "score_detail": {
        "theme_relevance": 4.0,
        "change_pct": 3.4,
        "trading_value": 8.2,
        "theme_strength": 35.4,
        "themes": [
          "기타제조"
        ]
      },
      "rank": 4,
      "market_cap": 7377389230000,
      "volume": 165915,
      "trading_value": 35792786000
    },
    {
      "code": "047050",
      "name": "포스코인터내셔널",
      "price": 48750,
      "change_pct": -1.91,
      "score": 47.7,
      "score_detail": {
        "theme_relevance": 16.0,
        "change_pct": 3.0,
        "trading_value": 4.3,
        "theme_strength": 24.4,
        "themes": [
          "음식료·담배",
          "오락·문화",
          "음식료·담배",
          "기타제조"
        ]
      },
      "rank": 5,
      "market_cap": 8576235915000,
      "volume": 378256,
      "trading_value": 18661275700,
      "themes": [
        {
          "code": "323",
          "name": "셰일가스(Shale Gas)"
        },
        {
          "code": "567",
          "name": "밸류업(24년 기업가치 제고계획 발표)"
        },
        {
          "code": "517",
          "name": "우크라이나 재건"
        },
        {
          "code": "568",
          "name": "코리아 밸류업 지수(Korea Value-up Index)"
        },
        {
          "code": "501",
          "name": "리비안(RIVIAN)"
        }
      ]
    }
  ],
  "params": {
    "active_themes": [
      {
        "name": "부동산",
        "change_pct": -0.72
      },
      {
        "name": "비금속",
        "change_pct": -0.75
      },
      {
        "name": "종이·목재",
        "change_pct": -0.8
      },
      {
        "name": "통신",
        "change_pct": -0.93
      },
      {
        "name": "운송·창고",
        "change_pct": -0.95
      },
      {
        "name": "음식료·담배",
        "change_pct": -1.17
      },
      {
        "name": "통신",
        "change_pct": -1.28
      },
      {
        "name": "오락·문화",
        "change_pct": -1.38
      },
      {
        "name": "음식료·담배",
        "change_pct": -1.6
      },
      {
        "name": "기타제조",
        "change_pct": -1.7
      }
    ],
    "theme_count": 10,
    "total_stocks": 96,
    "weights": {
      "theme_relevance": 40,
      "change_pct": 25,
      "trading_value": 20,
      "theme_strength": 15
    }
  },
  "simulation": null
}