[
  {
    "code": "004650",
    "name": "창해에탄올",
    "price": 12010,
    "change_pct": 15.93,
    "theme": "주류업(주정, 에탄올 등)"
  },
  {
    "code": "023150",
    "name": "MH에탄올",
    "price": 5280,
    "change_pct": 9.77,
    "theme": "주류업(주정, 에탄올 등)"
  },
  {
    "code": "276730",
    "name": "한울앤제주",
    "price": 870,
    "change_pct": 7.41,
    "theme": "주류업(주정, 에탄올 등)"
  },
  {
    "code": "023900",
    "name": "풍국주정",
    "price": 11140,
    "change_pct": 5.0,
    "theme": "주류업(주정, 에탄올 등)"
  },
  {
    "code": "018120",
    "name": "진로발효",
    "price": 18040,
    "change_pct": 2.27,
    "theme": "주류업(주정, 에탄올 등)"
  },
  {
    "code": "017890",
    "name": "한국알콜",
    "price": 10820,
    "change_pct": 1.6,
    "theme": "주류업(주정, 에탄올 등)"
  },
  {
    "code": "033920",
    "name": "무학",
    "price": 8720,
    "change_pct": 1.4,
    "theme": "주류업(주정, 에탄올 등)"
  },
  {
    "code": "000890",
    "name": "보해양조",
    "price": 428,
    "change_pct": 0.71,
    "theme": "주류업(주정, 에탄올 등)"
  },
  {
    "code": "000080",
    "name": "하이트진로",
    "price": 16770,
    "change_pct": 0.0,
    "theme": "주류업(주정, 에탄올 등)"
  },
  {
    "code": "005300",
    "name": "롯데칠성",
    "price": 114000,
    "change_pct": 0.0,
    "theme": "주류업(주정, 에탄올 등)"
  },
  {
    "code": "000140",
    "name": "하이트진로홀딩스",
    "price": 8980,
    "change_pct": -0.11,
    "theme": "주류업(주정, 에탄올 등)"
  },
  {
    "code": "405920",
    "name": "나라셀라",
    "price": 2605,
    "change_pct": -0.76,
    "theme": "주류업(주정, 에탄올 등)"
  },
  {
    "code": "043650",
    "name": "국순당",
    "price": 4080,
    "change_pct": -0.97,
    "theme": "주류업(주정, 에탄올 등)"
  }
]